biomomentum/__init__.py
biomomentum/analysis_dynamic.py
biomomentum/analysis_static.py
biomomentum/interpolation.py
biomomentum/ios.py
biomomentum/stats.py
biomomentum/utils.py
biomomentum/data/__init__.py
biomomentum/data/sveff_tab.mat
biomomentum-0.1.10.dist-info/METADATA
biomomentum-0.1.10.dist-info/WHEEL
biomomentum-0.1.10.dist-info/top_level.txt
biomomentum-0.1.10.dist-info/RECORD
