Metadata-Version: 2.4
Name: biomomentum
Version: 0.1.10
Summary: Mach-1 Analysis Functions
Home-page: https://github.com/RenatoC322/Biomomentum-functions/tree/main
Author: Renato Castillo
Author-email: castillo.renato@biomomentum.com
Classifier: Programming Language :: Python :: 3
Classifier: Programming Language :: Python :: 3.11
Classifier: License :: OSI Approved :: MIT License
Classifier: Operating System :: OS Independent
Requires-Python: >=3.11
Requires-Dist: numpy
Requires-Dist: pandas
Requires-Dist: scipy
Requires-Dist: scikit-learn
Requires-Dist: opencv-python
Dynamic: author
Dynamic: author-email
Dynamic: classifier
Dynamic: description
Dynamic: description-content-type
Dynamic: home-page
Dynamic: requires-dist
Dynamic: requires-python
Dynamic: summary
